{
  "key": "group_684709fc60e66",
  "title": "CMS Block: Specializations",
  "fields": [
    {
      "key": "field_68470bea8a1e0",
      "label": "Edge to Edge",
      "name": "edge_to_edge",
      "aria-label": "",
      "type": "true_false",
      "instructions": "",
      "required": 0,
      "conditional_logic": 0,
      "wrapper": {
        "width": "",
        "class": "",
        "id": ""
      },
      "message": "",
      "default_value": 0,
      "allow_in_bindings": 0,
      "ui_on_text": "",
      "ui_off_text": "",
      "ui": 1
    },
    {
      "key": "field_68470c068a1e1",
      "label": "Extend Container to almost Full Width",
      "name": "extend_container",
      "aria-label": "",
      "type": "true_false",
      "instructions": "",
      "required": 0,
      "conditional_logic": [
        [
          {
            "field": "field_68470bea8a1e0",
            "operator": "!=",
            "value": "1"
          }
        ]
      ],
      "wrapper": {
        "width": "",
        "class": "",
        "id": ""
      },
      "message": "",
      "default_value": 0,
      "allow_in_bindings": 0,
      "ui_on_text": "Almost Full Width",
      "ui_off_text": "Regular Sized Container",
      "ui": 1
    },
    {
      "key": "field_68470c318a1e2",
      "label": "Corners",
      "name": "corners",
      "aria-label": "",
      "type": "true_false",
      "instructions": "",
      "required": 0,
      "conditional_logic": [
        [
          {
            "field": "field_68470bea8a1e0",
            "operator": "!=",
            "value": "1"
          }
        ]
      ],
      "wrapper": {
        "width": "",
        "class": "",
        "id": ""
      },
      "message": "",
      "default_value": 0,
      "allow_in_bindings": 0,
      "ui_on_text": "Rounded",
      "ui_off_text": "Squared",
      "ui": 1
    },
    {
      "key": "field_684709fcd7c6a",
      "label": "Background Image",
      "name": "background_image",
      "aria-label": "",
      "type": "focuspoint",
      "instructions": "",
      "required": 0,
      "conditional_logic": 0,
      "wrapper": {
        "width": "",
        "class": "",
        "id": ""
      },
      "preview_size": "large",
      "library": "all",
      "min_width": "",
      "min_height": "",
      "min_size": "",
      "max_width": "",
      "max_height": "",
      "max_size": "",
      "mime_types": "",
      "allow_in_bindings": 0
    },
    {
      "key": "field_68470a17d7c6b",
      "label": "Headline",
      "name": "headline",
      "aria-label": "",
      "type": "text",
      "instructions": "",
      "required": 0,
      "conditional_logic": 0,
      "wrapper": {
        "width": "",
        "class": "",
        "id": ""
      },
      "default_value": "",
      "maxlength": "",
      "allow_in_bindings": 0,
      "placeholder": "",
      "prepend": "",
      "append": ""
    },
    {
      "key": "field_68470a20d7c6c",
      "label": "Description",
      "name": "description",
      "aria-label": "",
      "type": "wysiwyg",
      "instructions": "",
      "required": 0,
      "conditional_logic": 0,
      "wrapper": {
        "width": "",
        "class": "",
        "id": ""
      },
      "default_value": "",
      "allow_in_bindings": 0,
      "tabs": "all",
      "toolbar": "full",
      "media_upload": 1,
      "delay": 0
    },
    {
      "key": "field_68470a2ed7c6d",
      "label": "Specializations",
      "name": "specializations",
      "aria-label": "",
      "type": "repeater",
      "instructions": "",
      "required": 0,
      "conditional_logic": 0,
      "wrapper": {
        "width": "",
        "class": "",
        "id": ""
      },
      "layout": "table",
      "pagination": 0,
      "min": 0,
      "max": 0,
      "collapsed": "",
      "button_label": "Add Row",
      "rows_per_page": 20,
      "sub_fields": [
        {
          "key": "field_68470a41d7c6e",
          "label": "Icon",
          "name": "icon",
          "aria-label": "",
          "type": "font-awesome",
          "instructions": "",
          "required": 0,
          "conditional_logic": 0,
          "wrapper": {
            "width": "",
            "class": "",
            "id": ""
          },
          "icon_sets": [
            "solid",
            "regular",
            "brands"
          ],
          "custom_icon_set": "",
          "default_label": "",
          "default_value": "",
          "save_format": "class",
          "allow_null": 0,
          "show_preview": 1,
          "enqueue_fa": 0,
          "allow_in_bindings": 0,
          "fa_live_preview": "",
          "choices": [],
          "parent_repeater": "field_68470a2ed7c6d"
        },
        {
          "key": "field_68470a71d7c6f",
          "label": "Specialization",
          "name": "specialization",
          "aria-label": "",
          "type": "text",
          "instructions": "",
          "required": 0,
          "conditional_logic": 0,
          "wrapper": {
            "width": "",
            "class": "",
            "id": ""
          },
          "default_value": "",
          "maxlength": "",
          "allow_in_bindings": 0,
          "placeholder": "",
          "prepend": "",
          "append": "",
          "parent_repeater": "field_68470a2ed7c6d"
        },
        {
          "key": "field_68e4135b59c41",
          "label": "Link",
          "name": "link",
          "aria-label": "",
          "type": "link",
          "instructions": "",
          "required": 0,
          "conditional_logic": 0,
          "wrapper": {
            "width": "",
            "class": "",
            "id": ""
          },
          "return_format": "array",
          "allow_in_bindings": 0,
          "parent_repeater": "field_68470a2ed7c6d"
        }
      ]
    },
    {
      "key": "field_68470a81aebee",
      "label": "Button 1",
      "name": "button_1",
      "aria-label": "",
      "type": "link",
      "instructions": "",
      "required": 0,
      "conditional_logic": 0,
      "wrapper": {
        "width": "",
        "class": "",
        "id": ""
      },
      "return_format": "array",
      "allow_in_bindings": 0
    },
    {
      "key": "field_68470a89aebef",
      "label": "Button 2",
      "name": "button_2",
      "aria-label": "",
      "type": "link",
      "instructions": "",
      "required": 0,
      "conditional_logic": 0,
      "wrapper": {
        "width": "",
        "class": "",
        "id": ""
      },
      "return_format": "array",
      "allow_in_bindings": 0
    }
  ],
  "location": [
    [
      {
        "param": "block",
        "operator": "==",
        "value": "acf/cms-specializations"
      }
    ]
  ],
  "menu_order": 0,
  "position": "normal",
  "style": "default",
  "label_placement": "top",
  "instruction_placement": "label",
  "hide_on_screen": "",
  "active": true,
  "description": "",
  "show_in_rest": 0,
  "display_title": ""
}
